.gitignore
MANIFEST.in
bootstrap.py
buildout.cfg
setup.py
docs/HISTORY.txt
src/megrok/__init__.py
src/megrok.layout.egg-info/PKG-INFO
src/megrok.layout.egg-info/SOURCES.txt
src/megrok.layout.egg-info/dependency_links.txt
src/megrok.layout.egg-info/namespace_packages.txt
src/megrok.layout.egg-info/not-zip-safe
src/megrok.layout.egg-info/requires.txt
src/megrok.layout.egg-info/top_level.txt
src/megrok/layout/CREDITS.txt
src/megrok/layout/README.txt
src/megrok/layout/__init__.py
src/megrok/layout/components.py
src/megrok/layout/configure.zcml
src/megrok/layout/interfaces.py
src/megrok/layout/meta.py
src/megrok/layout/meta.zcml
src/megrok/layout/templates/default_display_form.pt
src/megrok/layout/templates/default_edit_form.pt
src/megrok/layout/tests/__init__.py
src/megrok/layout/tests/ftesting.zcml
src/megrok/layout/tests/test_package.py
src/megrok/layout/tests/test_readme.py
src/megrok/layout/tests/errors/__init__.py
src/megrok/layout/tests/errors/norenderortemplatelayout.py
src/megrok/layout/tests/errors/renderandtemplate.py
src/megrok/layout/tests/errors/samecontext.py
src/megrok/layout/tests/errors/renderandtemplate_templates/mylayout.pt
src/megrok/layout/tests/layout/__init__.py
src/megrok/layout/tests/layout/layout.py
src/megrok/layout/tests/layout/layoutlayers.py
src/megrok/layout/tests/layout/no_staticfolder.py
src/megrok/layout/tests/layout/specializedlayout.py
src/megrok/layout/tests/layout/staticfolder.py
src/megrok/layout/tests/layout/static_fixture/__init__.py
src/megrok/layout/tests/layout/static_fixture/simple.py
src/megrok/layout/tests/models/__init__.py
src/megrok/layout/tests/models/forms.py
src/megrok/layout/tests/models/message.py
src/megrok/layout/tests/models/page.py
src/megrok/layout/tests/models/url.py
src/megrok/layout/tests/models/templates/master.pt