Metadata-Version: 1.0
Name: megrok.layout
Version: 1.3
Summary: A layout component package for zope3 and Grok.
Home-page: http://pypi.python.org/pypi/megrok.layout
Author: Souheil Chelfouh
Author-email: trollfot@gmail.com
License: GPL
Keywords: grok layout zope3 pagelet theming
Platform: UNKNOWN
Classifier: Framework :: Zope3
Classifier: Programming Language :: Python
Classifier: Programming Language :: Zope
Classifier: Intended Audience :: Developers
Classifier: Development Status :: 5 - Production/Stable
Classifier: Topic :: Software Development :: Libraries :: Python Modules
